BuildYourOwnLispZhongwenban/README.md
BuildYourOwnLispZhongwenban/__init__.py
BuildYourOwnLispZhongwenban/__main__.py
BuildYourOwnLispZhongwenban/file.epub
BuildYourOwnLispZhongwenban/index.html
BuildYourOwnLispZhongwenban/css/__init__.py
BuildYourOwnLispZhongwenban/css/annotations.css
BuildYourOwnLispZhongwenban/css/main.css
BuildYourOwnLispZhongwenban/css/normalize.css
BuildYourOwnLispZhongwenban/css/popup.css
BuildYourOwnLispZhongwenban/font/__init__.py
BuildYourOwnLispZhongwenban/font/fontello.eot
BuildYourOwnLispZhongwenban/font/fontello.svg
BuildYourOwnLispZhongwenban/font/fontello.ttf
BuildYourOwnLispZhongwenban/font/fontello.woff
BuildYourOwnLispZhongwenban/img/__init__.py
BuildYourOwnLispZhongwenban/img/annotator-glyph-sprite.png
BuildYourOwnLispZhongwenban/img/annotator-icon-sprite.png
BuildYourOwnLispZhongwenban/img/apple-touch-icon.png
BuildYourOwnLispZhongwenban/img/cancelfullscreen.png
BuildYourOwnLispZhongwenban/img/close.png
BuildYourOwnLispZhongwenban/img/fullscreen.png
BuildYourOwnLispZhongwenban/img/loader.gif
BuildYourOwnLispZhongwenban/img/menu-icon.png
BuildYourOwnLispZhongwenban/img/save.png
BuildYourOwnLispZhongwenban/img/saved.png
BuildYourOwnLispZhongwenban/img/settings-s.png
BuildYourOwnLispZhongwenban/img/settings.png
BuildYourOwnLispZhongwenban/img/star.png
BuildYourOwnLispZhongwenban/js/__init__.py
BuildYourOwnLispZhongwenban/js/epub.js
BuildYourOwnLispZhongwenban/js/epub.min.js
BuildYourOwnLispZhongwenban/js/epub.min.map
BuildYourOwnLispZhongwenban/js/hooks.min.js
BuildYourOwnLispZhongwenban/js/hooks.min.map
BuildYourOwnLispZhongwenban/js/reader.js
BuildYourOwnLispZhongwenban/js/reader.js.map
BuildYourOwnLispZhongwenban/js/reader.min.js
BuildYourOwnLispZhongwenban/js/reader.min.map
BuildYourOwnLispZhongwenban/js/hooks/__init__.py
BuildYourOwnLispZhongwenban/js/hooks/extensions/__init__.py
BuildYourOwnLispZhongwenban/js/hooks/extensions/highlight.js
BuildYourOwnLispZhongwenban/js/libs/__init__.py
build_your_own_lisp_zhongwenban-2024.3.4.0.dist-info/METADATA
build_your_own_lisp_zhongwenban-2024.3.4.0.dist-info/WHEEL
build_your_own_lisp_zhongwenban-2024.3.4.0.dist-info/entry_points.txt
build_your_own_lisp_zhongwenban-2024.3.4.0.dist-info/top_level.txt
build_your_own_lisp_zhongwenban-2024.3.4.0.dist-info/RECORD
